mcp_feedback_enhanced/__init__.py
mcp_feedback_enhanced/__main__.py
mcp_feedback_enhanced/debug.py
mcp_feedback_enhanced/i18n.py
mcp_feedback_enhanced/server.py
mcp_feedback_enhanced/test_qt_gui.py
mcp_feedback_enhanced/test_web_ui.py
mcp_feedback_enhanced/gui/__init__.py
mcp_feedback_enhanced/gui/main.py
mcp_feedback_enhanced/gui/models/__init__.py
mcp_feedback_enhanced/gui/models/feedback.py
mcp_feedback_enhanced/gui/styles/__init__.py
mcp_feedback_enhanced/gui/styles/themes.py
mcp_feedback_enhanced/gui/tabs/__init__.py
mcp_feedback_enhanced/gui/tabs/about_tab.py
mcp_feedback_enhanced/gui/tabs/command_tab.py
mcp_feedback_enhanced/gui/tabs/feedback_tab.py
mcp_feedback_enhanced/gui/tabs/settings_tab.py
mcp_feedback_enhanced/gui/tabs/summary_tab.py
mcp_feedback_enhanced/gui/utils/__init__.py
mcp_feedback_enhanced/gui/utils/shortcuts.py
mcp_feedback_enhanced/gui/utils/utils.py
mcp_feedback_enhanced/gui/widgets/__init__.py
mcp_feedback_enhanced/gui/widgets/image_preview.py
mcp_feedback_enhanced/gui/widgets/image_upload.py
mcp_feedback_enhanced/gui/widgets/switch.py
mcp_feedback_enhanced/gui/widgets/text_edit.py
mcp_feedback_enhanced/gui/window/__init__.py
mcp_feedback_enhanced/gui/window/command_executor.py
mcp_feedback_enhanced/gui/window/config_manager.py
mcp_feedback_enhanced/gui/window/feedback_window.py
mcp_feedback_enhanced/gui/window/tab_manager.py
mcp_feedback_enhanced/locales/README.md
mcp_feedback_enhanced/locales/en/translations.json
mcp_feedback_enhanced/locales/zh-CN/translations.json
mcp_feedback_enhanced/locales/zh-TW/translations.json
mcp_feedback_enhanced/web/__init__.py
mcp_feedback_enhanced/web/main.py
mcp_feedback_enhanced/web/locales/en/translation.json
mcp_feedback_enhanced/web/locales/zh-CN/translation.json
mcp_feedback_enhanced/web/locales/zh-TW/translation.json
mcp_feedback_enhanced/web/models/__init__.py
mcp_feedback_enhanced/web/models/feedback_result.py
mcp_feedback_enhanced/web/models/feedback_session.py
mcp_feedback_enhanced_lixd-2.2.3.dist-info/METADATA
mcp_feedback_enhanced_lixd-2.2.3.dist-info/WHEEL
mcp_feedback_enhanced_lixd-2.2.3.dist-info/entry_points.txt
mcp_feedback_enhanced_lixd-2.2.3.dist-info/licenses/LICENSE
mcp_feedback_enhanced_lixd-2.2.3.dist-info/RECORD
